llmmodelsapi/__init__.py
llmmodelsapi-1.1.0.dist-info/LICENSE.txt
llmmodelsapi-1.1.0.dist-info/METADATA
llmmodelsapi-1.1.0.dist-info/WHEEL
llmmodelsapi-1.1.0.dist-info/top_level.txt
llmmodelsapi-1.1.0.dist-info/RECORD
