Metadata-Version: 2.1
Name: llmmodelsapi
Version: 1.1.0
Summary: SDK for interfacing with core models hosted by LLM Solutions
Home-page: https://github.com/llm-solutions/LLM-API-Express-SDK-Python
Download-URL: https://github.com/llm-solutions/LLM-API-Express-SDK-Python/archive/refs/tags/v1.1.0.tar.gz
Author: Matthieu Moullec
Author-email: matthieu.moullec.perso@gmail.com
License: MIT
Keywords: Large Language Model,LLM,API
Classifier: Development Status :: 4 - Beta
Classifier: Intended Audience :: Developers
Classifier: Topic :: Software Development :: Build Tools
Classifier: License :: OSI Approved :: MIT License
Classifier: Programming Language :: Python :: 3.9
Classifier: Programming Language :: Python :: 3.10
Classifier: Programming Language :: Python :: 3.11
License-File: LICENSE.txt
Requires-Dist: requests
